AUTHORS.rst
CONTRIBUTING.rst
HISTORY.rst
LICENSE
MANIFEST.in
README.rst
setup.cfg
setup.py
av_slice/__init__.py
av_slice/audio.py
av_slice/cli.py
av_slice/video.py
av_slice.egg-info/PKG-INFO
av_slice.egg-info/SOURCES.txt
av_slice.egg-info/dependency_links.txt
av_slice.egg-info/entry_points.txt
av_slice.egg-info/not-zip-safe
av_slice.egg-info/requires.txt
av_slice.egg-info/top_level.txt
docs/Makefile
docs/authors.rst
docs/conf.py
docs/contributing.rst
docs/history.rst
docs/index.rst
docs/installation.rst
docs/make.bat
docs/readme.rst
docs/usage.rst
tests/__init__.py
tests/test_audio.py
tests/test_cli.py
tests/test_video.py