Metadata-Version: 1.1
Name: av-slice
Version: 0.1.11
Summary: Automatic video editing
Home-page: https://github.com/Hixan/av_slice
Author: Alex Elias
Author-email: alex.88.elias@gmail.com
License: MIT license
Keywords: av_slice
Platform: UNKNOWN
Classifier: Development Status :: 2 - Pre-Alpha
Classifier: Intended Audience :: Developers
Classifier: License :: OSI Approved :: MIT License
Classifier: Natural Language :: English
Classifier: Programming Language :: Python :: 3.6
Classifier: Programming Language :: Python :: 3.7
Classifier: Programming Language :: Python :: 3.8
